mylib_018/__init__.py
mylib_018-0.1.dist-info/LICENSE.txt
mylib_018-0.1.dist-info/METADATA
mylib_018-0.1.dist-info/WHEEL
mylib_018-0.1.dist-info/top_level.txt
mylib_018-0.1.dist-info/RECORD
