Metadata-Version: 2.1
Name: mylib-018
Version: 0.1
Summary: This program is to calculate square of a given no.
Author: Ketan
Author-email: ketan.suradkar56@gmail.com
Classifier: Programming Language :: Python :: 3
Classifier: License :: OSI Approved :: MIT License
Classifier: Operating System :: OS Independent
License-File: LICENSE.txt
